manzara/__init__.py
manzara/landscapes.py
manzara/seqs.py
manzara-0.1.2.dist-info/licenses/LICENSE
manzara-0.1.2.dist-info/METADATA
manzara-0.1.2.dist-info/WHEEL
manzara-0.1.2.dist-info/top_level.txt
manzara-0.1.2.dist-info/RECORD
