Metadata-Version: 2.4
Name: manzara
Version: 0.1.2
Summary: A Python package for simulating fitness landscapes
Author: berkalpay
Project-URL: Homepage, https://github.com/berkalpay/manzara
Classifier: Programming Language :: Python :: 3
Requires-Python: >=3.12
License-File: LICENSE
Dynamic: license-file
